MANIFEST.in
README.rst
setup.py
collective/.DS_Store
collective/__init__.py
collective/__init__.pyc
collective.ptg.s3slider.egg-info/PKG-INFO
collective.ptg.s3slider.egg-info/SOURCES.txt
collective.ptg.s3slider.egg-info/dependency_links.txt
collective.ptg.s3slider.egg-info/entry_points.txt
collective.ptg.s3slider.egg-info/namespace_packages.txt
collective.ptg.s3slider.egg-info/not-zip-safe
collective.ptg.s3slider.egg-info/requires.txt
collective.ptg.s3slider.egg-info/top_level.txt
collective/ptg/.DS_Store
collective/ptg/__init__.py
collective/ptg/__init__.pyc
collective/ptg/s3slider/.DS_Store
collective/ptg/s3slider/__init__.py
collective/ptg/s3slider/__init__.pyc
collective/ptg/s3slider/configure.zcml
collective/ptg/s3slider/i18n.sh
collective/ptg/s3slider/s3slider.pt
collective/ptg/s3slider/locales/.DS_Store
collective/ptg/s3slider/locales/collective.ptg.s3slider.pot
collective/ptg/s3slider/locales/manual.pot
collective/ptg/s3slider/locales/de/LC_MESSAGES/collective.ptg.s3slider.mo
collective/ptg/s3slider/locales/de/LC_MESSAGES/collective.ptg.s3slider.po
collective/ptg/s3slider/locales/es/LC_MESSAGES/collective.ptg.s3slider.mo
collective/ptg/s3slider/locales/es/LC_MESSAGES/collective.ptg.s3slider.po
collective/ptg/s3slider/locales/eu/LC_MESSAGES/collective.ptg.s3slider.mo
collective/ptg/s3slider/locales/eu/LC_MESSAGES/collective.ptg.s3slider.po
collective/ptg/s3slider/locales/fi/LC_MESSAGES/collective.ptg.s3slider.mo
collective/ptg/s3slider/locales/fi/LC_MESSAGES/collective.ptg.s3slider.po
collective/ptg/s3slider/locales/fr/LC_MESSAGES/collective.ptg.s3slider.mo
collective/ptg/s3slider/locales/fr/LC_MESSAGES/collective.ptg.s3slider.po
collective/ptg/s3slider/locales/it/LC_MESSAGES/collective.ptg.s3slider.mo
collective/ptg/s3slider/locales/it/LC_MESSAGES/collective.ptg.s3slider.po
collective/ptg/s3slider/locales/nl/.DS_Store
collective/ptg/s3slider/locales/nl/LC_MESSAGES/collective.ptg.s3slider.mo
collective/ptg/s3slider/locales/nl/LC_MESSAGES/collective.ptg.s3slider.po
collective/ptg/s3slider/locales/no/.DS_Store
collective/ptg/s3slider/locales/no/LC_MESSAGES/.DS_Store
collective/ptg/s3slider/locales/no/LC_MESSAGES/collective.ptg.s3slider.mo
collective/ptg/s3slider/locales/no/LC_MESSAGES/collective.ptg.s3slider.po
collective/ptg/s3slider/locales/pt_BR/LC_MESSAGES/collective.ptg.s3slider.mo
