Metadata-Version: 1.0
Name: collective.ptg.s3slider
Version: 1.0.8
Summary: Adds s3slider to collective.plonetruegallery
Home-page: https://github.com/collective/collective.ptg.s3slider
Author: Nathan Van Gheem
Author-email: vangheem@gmail.com
License: GPL
Keywords: plone plonetruegallery addon
Platform: UNKNOWN
Classifier: Framework :: Plone
Classifier: Programming Language :: Python
